koleksyon/__init__.py
koleksyon/dta.py
koleksyon/encode.py
koleksyon/gbm.py
koleksyon/lib.py
koleksyon/mcmc.cpython-38-darwin.so
koleksyon/mltree.py
koleksyon/sim.py
koleksyon-0.0.7.data/data/my_data/cars.csv
koleksyon-0.0.7.dist-info/LICENSE.txt
koleksyon-0.0.7.dist-info/METADATA
koleksyon-0.0.7.dist-info/WHEEL
koleksyon-0.0.7.dist-info/entry_points.txt
koleksyon-0.0.7.dist-info/top_level.txt
koleksyon-0.0.7.dist-info/RECORD
